catmapper/README.MD
catmapper/__init__.py
catmapper/requirements.txt
catmapper/thirdparty.json
catmapper-0.10.dist-info/LICENSE.rst
catmapper-0.10.dist-info/METADATA
catmapper-0.10.dist-info/WHEEL
catmapper-0.10.dist-info/top_level.txt
catmapper-0.10.dist-info/RECORD
