Metadata-Version: 2.1
Name: catmapper
Version: 0.10
Summary: Maps the elements of an iterable to categories using bisect
Home-page: https://github.com/hansalemaos/catmapper
Author: Johannes Fischer
Author-email: aulasparticularesdealemaosp@gmail.com
License: MIT
Keywords: bisect,mapping
Classifier: Development Status :: 4 - Beta
Classifier: Programming Language :: Python :: 3 :: Only
Classifier: Programming Language :: Python :: 3.10
Classifier: Topic :: Software Development :: Libraries :: Python Modules
Classifier: Topic :: Utilities
License-File: LICENSE.rst
Requires-Dist: isiter
